organizze_mcp/__init__.py
organizze_mcp/main.py
organizze_mcp-0.1.12.dist-info/METADATA
organizze_mcp-0.1.12.dist-info/WHEEL
organizze_mcp-0.1.12.dist-info/entry_points.txt
organizze_mcp-0.1.12.dist-info/top_level.txt
organizze_mcp-0.1.12.dist-info/RECORD
