Metadata-Version: 2.4
Name: organizze-mcp
Version: 0.1.12
Summary: Add your description here
Requires-Python: >=3.11
Requires-Dist: dotenv>=0.9.9
Requires-Dist: fastmcp>=2.3.3
Requires-Dist: requests>=2.32.3
